odoo/addons/stock_available_immediately/README.rst
odoo/addons/stock_available_immediately/__init__.py
odoo/addons/stock_available_immediately/__manifest__.py
odoo/addons/stock_available_immediately/i18n/ca.po
odoo/addons/stock_available_immediately/i18n/cs_CZ.po
odoo/addons/stock_available_immediately/i18n/de.po
odoo/addons/stock_available_immediately/i18n/el_GR.po
odoo/addons/stock_available_immediately/i18n/es.po
odoo/addons/stock_available_immediately/i18n/es_ES.po
odoo/addons/stock_available_immediately/i18n/es_MX.po
odoo/addons/stock_available_immediately/i18n/eu.po
odoo/addons/stock_available_immediately/i18n/fi.po
odoo/addons/stock_available_immediately/i18n/fr.po
odoo/addons/stock_available_immediately/i18n/fr_CH.po
odoo/addons/stock_available_immediately/i18n/gl.po
odoo/addons/stock_available_immediately/i18n/hr.po
odoo/addons/stock_available_immediately/i18n/hr_HR.po
odoo/addons/stock_available_immediately/i18n/it.po
odoo/addons/stock_available_immediately/i18n/nl.po
odoo/addons/stock_available_immediately/i18n/nl_NL.po
odoo/addons/stock_available_immediately/i18n/pt.po
odoo/addons/stock_available_immediately/i18n/pt_BR.po
odoo/addons/stock_available_immediately/i18n/ro.po
odoo/addons/stock_available_immediately/i18n/ru.po
odoo/addons/stock_available_immediately/i18n/sl.po
odoo/addons/stock_available_immediately/i18n/stock_available_immediately.pot
odoo/addons/stock_available_immediately/i18n/tr.po
odoo/addons/stock_available_immediately/i18n/tr_TR.po
odoo/addons/stock_available_immediately/i18n/vi_VN.po
odoo/addons/stock_available_immediately/i18n/zh_CN.po
odoo/addons/stock_available_immediately/models/__init__.py
odoo/addons/stock_available_immediately/models/product_product.py
odoo/addons/stock_available_immediately/readme/CONTRIBUTORS.rst
odoo/addons/stock_available_immediately/readme/DESCRIPTION.rst
odoo/addons/stock_available_immediately/static/description/icon.png
odoo/addons/stock_available_immediately/static/description/index.html
odoo12_addon_stock_available_immediately-12.0.1.0.1.dist-info/METADATA
odoo12_addon_stock_available_immediately-12.0.1.0.1.dist-info/WHEEL
odoo12_addon_stock_available_immediately-12.0.1.0.1.dist-info/top_level.txt
odoo12_addon_stock_available_immediately-12.0.1.0.1.dist-info/RECORD
