Metadata-Version: 2.1
Name: odoo12-addon-stock-available-immediately
Version: 12.0.1.0.1
Summary: Ignore planned receptions in quantity available to promise
Home-page: https://github.com/OCA/stock-logistics-warehouse
Author: Camptocamp,Sodexis,Odoo Community Association (OCA),Sergio Díaz
Author-email: support@odoo-community.org
License: AGPL-3
Platform: UNKNOWN
Classifier: Programming Language :: Python
Classifier: Framework :: Odoo
Classifier: Framework :: Odoo :: 12.0
Classifier: License :: OSI Approved :: GNU Affero General Public License v3
Requires-Python: >=3.5
Requires-Dist: odoo12-addon-stock-available
Requires-Dist: odoo (<12.1dev,>=12.0a)
